neuroimage_denoiser/__main__.py
neuroimage_denoiser/filter_h5.py
neuroimage_denoiser/model/__init__.py
neuroimage_denoiser/model/denoise.py
neuroimage_denoiser/model/gridsearch_train.py
neuroimage_denoiser/model/modelparts.py
neuroimage_denoiser/model/modelwrapper.py
neuroimage_denoiser/model/train.py
neuroimage_denoiser/model/unet.py
neuroimage_denoiser/tests/__init__.py
neuroimage_denoiser/utils/__init__.py
neuroimage_denoiser/utils/activitymap.py
neuroimage_denoiser/utils/convert.py
neuroimage_denoiser/utils/copy_folder_structure.py
neuroimage_denoiser/utils/dataloader.py
neuroimage_denoiser/utils/evaluate_model.py
neuroimage_denoiser/utils/inferencespeed.py
neuroimage_denoiser/utils/normalization.py
neuroimage_denoiser/utils/open_file.py
neuroimage_denoiser/utils/plot.py
neuroimage_denoiser/utils/trainfiles.py
neuroimage_denoiser/utils/write_file.py
neuroimage_denoiser-0.1.5.dist-info/LICENSE
neuroimage_denoiser-0.1.5.dist-info/METADATA
neuroimage_denoiser-0.1.5.dist-info/WHEEL
neuroimage_denoiser-0.1.5.dist-info/RECORD
