Metadata-Version: 2.1
Name: neuroimage_denoiser
Version: 0.1.5
Summary: 
Author: Stephan Weißbach
Author-email: s.weissbach@uni-mainz.de
Requires-Python: >=3.10,<3.11
Classifier: Programming Language :: Python :: 3
Classifier: Programming Language :: Python :: 3.10
Requires-Dist: alive-progress (>=3.1.5,<4.0.0)
Requires-Dist: h5py (>=3.10.0,<4.0.0)
Requires-Dist: matplotlib (>=3.7.1,<4.0.0)
Requires-Dist: nd2 (>=0.8.1,<0.9.0)
Requires-Dist: numpy (>=1.26.1,<2.0.0)
Requires-Dist: pandas (>=2.1.1,<3.0.0)
Requires-Dist: roifile (>=2024.3.20,<2025.0.0)
Requires-Dist: scikit-image (>=0.23.2,<0.24.0)
Requires-Dist: scipy (>=1.11.3,<2.0.0)
Requires-Dist: tifffile (>=2023.4.12,<2024.0.0)
Requires-Dist: torch (>=2.1.1,<3.0.0)
Requires-Dist: torchaudio (>=2.1.1,<3.0.0)
Requires-Dist: torchvision (>=0.16.1,<0.17.0)
Requires-Dist: tqdm (>=4.65.0,<5.0.0)
